{
	"$schema": "https://tonytools.win/schemas/dlge.schema.json",
	"hash": "[assembly:/localization/hitman6/conversations/_test_dialogue/evergreen_d/be_escaped.sweetdialog?/be_escaped_diana_001.sweetdialogitem].pc_dialogevent",
	"DITL": "00B7E83B2B5BFE20",
	"CLNG": "00E3CBB0725ED16C",
	"rootContainer": {
		"type": "WavFile",
		"wavName": "be_escaped_diana_001",
		"soundtag": "Voiceover_Handler",
		"defaultWav": "[assembly:/sound/wwise/originals/voices/english(us)/_test_dialogue/evergreen_d/be_escaped_diana_001.wav].pc_wes",
		"defaultFfx": "[assembly:/_pro/facefx/exported_animation/english(us)/_test_dialogue/evergreen_d/be_escaped_diana_001.animset].pc_animset",
		"languages": {
			"en": "//[DIANA]\\\\//(0,31)\\\\We lost them 47. Our clients won't be pleased.",
			"fr": "//[DIANA]\\\\//(0,31)\\\\We lost them 47. Our clients won't be pleased.",
			"it": "//[DIANA]\\\\//(0,31)\\\\We lost them 47. Our clients won't be pleased.",
			"de": "//[DIANA]\\\\//(0,31)\\\\Wir haben sie verloren, 47. Unsere Klienten werden nicht begeistert sein.",
			"es": "//[DIANA]\\\\//(0,31)\\\\We lost them 47. Our clients won't be pleased.",
			"ru": "//[DIANA]\\\\//(0,31)\\\\Мы их упустили, 47. Наши клиенты будут недовольны.",
			"cn": "//[DIANA]\\\\//(0,31)\\\\我们弄丢他们了，47。我们的客户不会高兴的。",
			"tc": "//[DIANA]\\\\//(0,31)\\\\我們失去了他們，47。我們的客戶會不高興的。",
			"jp": "//[DIANA]\\\\//(0,31)\\\\We lost them 47. Our clients won't be pleased."
		}
	}
}
